ztmi_inst/__init__.py
ztmi_inst/cmd_build.json
ztmi_inst/commands/__init__.py
ztmi_inst/commands/command.py
ztmi_inst/commands/custom_commands.py
ztmi_inst/commands/DMM6000/__init__.py
ztmi_inst/commands/DMM6000/dmm6000_commands.py
ztmi_inst/commands/DMM6000/measure_config_commands.py
ztmi_inst/commands/DMM6000/sense_commands.py
ztmi_inst/commands/ieee_commands.py
ztmi_inst/commands/zds/__init__.py
ztmi_inst/commands/zds/ch_commands.py
ztmi_inst/commands/zds/measure_commands.py
ztmi_inst/commands/zds/root_commands.py
ztmi_inst/commands/zds/trigger_commands.py
ztmi_inst/commands/zds/zds2024/__init__.py
ztmi_inst/commands/zds/zds2024/zds2024_commands.py
ztmi_inst/commands/zds/zds5054/__init__.py
ztmi_inst/commands/zds/zds5054/zds5054_commands.py
ztmi_inst/drivers/__init__.py
ztmi_inst/drivers/driver.py
ztmi_inst/drivers/inst_device_mapping.py
ztmi_inst/drivers/multimeter/__init__.py
ztmi_inst/drivers/multimeter/dmm6000.py
ztmi_inst/drivers/oscillograph/__init__.py
ztmi_inst/drivers/oscillograph/osc_driver.py
ztmi_inst/drivers/oscillograph/zds/__init__.py
ztmi_inst/drivers/oscillograph/zds/zds2024/__init__.py
ztmi_inst/drivers/oscillograph/zds/zds2024/zds2024c.py
ztmi_inst/drivers/oscillograph/zds/zds5054/__init__.py
ztmi_inst/drivers/oscillograph/zds/zds5054/zds5054pro.py
ztmi_inst/drivers/unknown_inst.py
ztmi_inst/example.py
ztmi_inst/inst_manager.py
ztmi_inst-0.2.0.dist-info/LICENSE
ztmi_inst-0.2.0.dist-info/METADATA
ztmi_inst-0.2.0.dist-info/WHEEL
ztmi_inst-0.2.0.dist-info/RECORD
